mha_toolbox/__init__.py
mha_toolbox/__main__.py
mha_toolbox/advanced_hybrid.py
mha_toolbox/advanced_visualization.py
mha_toolbox/algorithm_categories.py
mha_toolbox/algorithm_recommender.py
mha_toolbox/base.py
mha_toolbox/beginner_mode.py
mha_toolbox/benchmarks.py
mha_toolbox/cli.py
mha_toolbox/complete_algorithm_registry.py
mha_toolbox/complete_algorithms.py
mha_toolbox/comprehensive_dashboard.py
mha_toolbox/comprehensive_exporter.py
mha_toolbox/csv_session_manager.py
mha_toolbox/demo_system.py
mha_toolbox/detailed_results_collector.py
mha_toolbox/duplicate.py
mha_toolbox/enhanced_runner.py
mha_toolbox/enhanced_session_manager.py
mha_toolbox/enhanced_visualizer.py
mha_toolbox/extended_algorithms.py
mha_toolbox/feature_integration.py
mha_toolbox/frontend.py
mha_toolbox/hybrid.py
mha_toolbox/hybrid_algorithms.py
mha_toolbox/hyperparameter_config.py
mha_toolbox/hyperparameter_tuning.py
mha_toolbox/intelligent_session_manager.py
mha_toolbox/landing_page.py
mha_toolbox/mega_algorithms.py
mha_toolbox/npz_comparator.py
mha_toolbox/persistent_state.py
mha_toolbox/professional_exporter.py
mha_toolbox/professional_visualizer.py
mha_toolbox/realtime_visualizer.py
mha_toolbox/results_manager.py
mha_toolbox/robust_optimization.py
mha_toolbox/session_controller.py
mha_toolbox/simple_api.py
mha_toolbox/toolbox.py
mha_toolbox/ui.py
mha_toolbox/user_profile.py
mha_toolbox/user_profile_optimized.py
mha_toolbox/algorithms/__init__.py
mha_toolbox/algorithms/abc.py
mha_toolbox/algorithms/aco.py
mha_toolbox/algorithms/aeo.py
mha_toolbox/algorithms/afsa.py
mha_toolbox/algorithms/alo.py
mha_toolbox/algorithms/alo_new.py
mha_toolbox/algorithms/ants.py
mha_toolbox/algorithms/ao.py
mha_toolbox/algorithms/aoa.py
mha_toolbox/algorithms/as_ant.py
mha_toolbox/algorithms/aso.py
mha_toolbox/algorithms/ba.py
mha_toolbox/algorithms/bat.py
mha_toolbox/algorithms/bbbc.py
mha_toolbox/algorithms/bbo.py
mha_toolbox/algorithms/bfo.py
mha_toolbox/algorithms/bh.py
mha_toolbox/algorithms/boa.py
mha_toolbox-2.0.2.dist-info/licenses/LICENSE
mha_toolbox-2.0.2.dist-info/METADATA
mha_toolbox-2.0.2.dist-info/WHEEL
mha_toolbox-2.0.2.dist-info/entry_points.txt
mha_toolbox-2.0.2.dist-info/top_level.txt
mha_toolbox-2.0.2.dist-info/RECORD
