Metadata-Version: 2.4
Name: mha-toolbox
Version: 2.0.2
Summary: Professional Metaheuristic Algorithm Library with 36+ algorithms, hybrid combinations, and comprehensive analysis tools
Home-page: https://github.com/Achyut103040/MHA-Algorithm
Author: MHA Development Team
Author-email: MHA Development Team <mha.toolbox@gmail.com>
Maintainer-email: MHA Development Team <mha.toolbox@gmail.com>
License: MIT License
Project-URL: Homepage, https://github.com/Achyut103040/MHA-Algorithm
Project-URL: Documentation, https://github.com/Achyut103040/MHA-Algorithm/wiki
Project-URL: Repository, https://github.com/Achyut103040/MHA-Algorithm
Project-URL: Bug Tracker, https://github.com/Achyut103040/MHA-Algorithm/issues
Keywords: metaheuristic,optimization,evolutionary-algorithm,swarm-intelligence,feature-selection,machine-learning,artificial-intelligence,bio-inspired,physics-based,hybrid-algorithms,pso,gwo,sca,woa,ga,de
Classifier: Development Status :: 5 - Production/Stable
Classifier: Intended Audience :: Science/Research
Classifier: Intended Audience :: Developers
Classifier: License :: OSI Approved :: MIT License
Classifier: Operating System :: OS Independent
Classifier: Programming Language :: Python :: 3
Classifier: Programming Language :: Python :: 3.8
Classifier: Programming Language :: Python :: 3.9
Classifier: Programming Language :: Python :: 3.10
Classifier: Programming Language :: Python :: 3.11
Classifier: Programming Language :: Python :: 3.12
Classifier: Topic :: Scientific/Engineering :: Artificial Intelligence
Classifier: Topic :: Scientific/Engineering :: Mathematics
Classifier: Topic :: Software Development :: Libraries :: Python Modules
Requires-Python: >=3.8
License-File: LICENSE
Requires-Dist: numpy>=1.19.0
Requires-Dist: pandas>=1.2.0
Requires-Dist: matplotlib>=3.3.0
Requires-Dist: seaborn>=0.11.0
Requires-Dist: scikit-learn>=0.24.0
Requires-Dist: scipy>=1.6.0
Requires-Dist: joblib>=1.0.0
Requires-Dist: tqdm>=4.60.0
Requires-Dist: click>=8.0.0
Provides-Extra: web
Requires-Dist: streamlit>=1.25.0; extra == "web"
Requires-Dist: plotly>=5.0.0; extra == "web"
Requires-Dist: dash>=2.0.0; extra == "web"
Provides-Extra: jupyter
Requires-Dist: jupyter>=1.0.0; extra == "jupyter"
Requires-Dist: ipython>=7.0.0; extra == "jupyter"
Requires-Dist: notebook>=6.0.0; extra == "jupyter"
Provides-Extra: advanced
Requires-Dist: tensorflow>=2.6.0; extra == "advanced"
Requires-Dist: torch>=1.9.0; extra == "advanced"
Requires-Dist: optuna>=2.10.0; extra == "advanced"
Requires-Dist: hyperopt>=0.2.5; extra == "advanced"
Provides-Extra: dev
Requires-Dist: pytest>=6.0.0; extra == "dev"
Requires-Dist: pytest-cov>=2.10.0; extra == "dev"
Requires-Dist: black>=21.0.0; extra == "dev"
Requires-Dist: flake8>=3.8.0; extra == "dev"
Requires-Dist: sphinx>=4.0.0; extra == "dev"
Requires-Dist: sphinx-rtd-theme>=1.0.0; extra == "dev"
Provides-Extra: all
Requires-Dist: streamlit>=1.25.0; extra == "all"
Requires-Dist: plotly>=5.0.0; extra == "all"
Requires-Dist: dash>=2.0.0; extra == "all"
Requires-Dist: jupyter>=1.0.0; extra == "all"
Requires-Dist: ipython>=7.0.0; extra == "all"
Requires-Dist: notebook>=6.0.0; extra == "all"
Requires-Dist: tensorflow>=2.6.0; extra == "all"
Requires-Dist: torch>=1.9.0; extra == "all"
Requires-Dist: optuna>=2.10.0; extra == "all"
Requires-Dist: hyperopt>=0.2.5; extra == "all"
Requires-Dist: pytest>=6.0.0; extra == "all"
Requires-Dist: pytest-cov>=2.10.0; extra == "all"
Requires-Dist: black>=21.0.0; extra == "all"
Requires-Dist: flake8>=3.8.0; extra == "all"
Requires-Dist: sphinx>=4.0.0; extra == "all"
Requires-Dist: sphinx-rtd-theme>=1.0.0; extra == "all"
Dynamic: author
Dynamic: home-page
Dynamic: license-file
Dynamic: requires-python
